src/BuildYaml.py
src/ReadConfig.py
src/__init__.py
src/data_access.py
src/excel_writer.py
src/exceptions.py
src/main.py
src/models.py
src/transformations.py
src/workflow_manager.py
wireviz_yaml_generator-0.1.0.dist-info/METADATA
wireviz_yaml_generator-0.1.0.dist-info/WHEEL
wireviz_yaml_generator-0.1.0.dist-info/entry_points.txt
wireviz_yaml_generator-0.1.0.dist-info/licenses/LICENSE
wireviz_yaml_generator-0.1.0.dist-info/RECORD
