Metadata-Version: 2.4
Name: wireviz-yaml-generator
Version: 0.1.0
Summary: Generate WireViz YAML files and manufacturing documentation from SQLite electrical design databases
Project-URL: Homepage, https://github.com/OleJBondahl/wireviz_yaml_generator
Project-URL: Documentation, https://olejbondahl.github.io/wireviz_yaml_generator/
Project-URL: Repository, https://github.com/OleJBondahl/wireviz_yaml_generator
Project-URL: Issues, https://github.com/OleJBondahl/wireviz_yaml_generator/issues
Author-email: Ole Johan Bondahl <your.email@example.com>
License: MIT
License-File: LICENSE
Keywords: bom,electrical,harness,manufacturing,wireviz,wiring-diagram,yaml
Classifier: Development Status :: 4 - Beta
Classifier: Intended Audience :: Developers
Classifier: Intended Audience :: Manufacturing
Classifier: License :: OSI Approved :: MIT License
Classifier: Programming Language :: Python :: 3
Classifier: Programming Language :: Python :: 3.10
Classifier: Programming Language :: Python :: 3.11
Classifier: Programming Language :: Python :: 3.12
Classifier: Programming Language :: Python :: 3.13
Classifier: Topic :: Scientific/Engineering :: Electronic Design Automation (EDA)
Classifier: Topic :: Software Development :: Code Generators
Requires-Python: >=3.10
Requires-Dist: openpyxl>=3.0
Requires-Dist: pandas>=2.0
Requires-Dist: pyyaml>=6.0
Requires-Dist: wireviz>=0.4.1
Provides-Extra: dev
Requires-Dist: pytest-cov>=4.0; extra == 'dev'
Requires-Dist: pytest>=7.0; extra == 'dev'
